{"dokumentstatus":{"dokument":{"hangar_id":"2348617","dok_id":"GN0969","rm":"1999/2000","beteckning":"69","doktyp":"prot","typ":"prot","subtyp":null,"tempbeteckning":null,"organ":null,"mottagare":null,"nummer":"69","slutnummer":"0","datum":"2000-02-18 00:00:00","systemdatum":"2005-10-27 12:17:22","publicerad":"2000-02-18 00:00:00","titel":"Riksdagens snabbprotokoll 1999/2000:69 Fredagen den 18 februari","subtitel":null,"status":null,"htmlformat":null,"relaterat_id":null,"source":"webbnav","sourceid":"{EA072C1F-3078-4E76-A36E-714829F0E3C2}","dokument_url_text":"http://data.riksdagen.se/dokument/GN0969/text","dokument_url_html":"http://data.riksdagen.se/dokument/GN0969","dokumentstatus_url_xml":"http://data.riksdagen.se/dokumentstatus/GN0969","html":"\r\n<br><div class=\"sidhuvud_publikation\">Riksdagens snabbprotokoll</div>\r\n<div class=\"sidhuvud_beteckning\">Protokoll 1999/2000:69</div>\r\n<div class=\"sidhuvud_datum\">Fredagen den 18 februari</div>\r\n<div class=\"sidhuvud_klockslag\">Kl. 9.00 - 9.26</div>\r\n<hr class=\"sidhuvud_linje\">\r\n<pre>Det justerade protokollet beräknas utkomma om 3 veckor</pre><pre>----------------------------------------------------------------------</pre><pre>1 §  Meddelande om aktuell debatt</pre><pre>Förste vice talmannen meddelade att på begäran\r\nav Miljöpartiet de Grönas riksdagsgrupp skulle aktu-\r\nell debatt om TV-kanalernas pornografiska utbud\r\nanordnas torsdagen den 24 februari kl. 12.00.\r\nFrån regeringen skulle kulturminister Marita Ulv-\r\nskog delta.</pre><pre>Den inkomna skrivelsen hade följande lydelse:</pre><pre>Till talmannen</pre><pre>Begäran om aktuell debatt\r\nMiljöpartiet de Gröna begär att en aktuell debatt\r\nanordnas om TV-kanalernas pornografiska utbud.\r\nAnledningen till detta är den senaste tidens samhälls-\r\ndebatt i frågan och den oklarhet som råder kring nu-\r\nvarande lagstiftning och betal-TV-kanalernas sänd-\r\nningar av grova pornografiska filmer.\r\nStockholm den 15 februari 2000\r\nMiljöpartiet de Gröna\r\nMarianne Samuelsson\r\nGruppledare</pre><pre>2 §  Meddelande om ändringar i kammarens\r\nsammanträdesplan</pre><pre>Förste vice talmannen meddelade att ett medde-\r\nlande om ändringar i kammarens sammanträdesplan\r\ndelats ut till kammarens ledamöter.</pre><pre>3 §  Meddelande om plan för kammarens sam-\r\nmanträden</pre><pre>Förste vice talmannen meddelade att en plan för\r\nkammarens sammanträden under tiden den 6 mars-\r\n15 juni 2000 delats ut till kammarens ledamöter.</pre><pre>4 §  Beslut om senaste dag för avlämnande av\r\npropositioner</pre><pre>I enlighet med 3 kap. 3 § riksdagsordningen hade\r\ntalmannen föreslagit att propositioner som regeringen\r\navser skall behandlas under innevarande riksmöte och\r\nför vilka särskild tidpunkt inte är föreskriven skulle\r\navlämnas senast onsdagen den 22 mars.</pre><pre>Kammaren biföll detta förslag.</pre><pre>5 §  Senaste dag för framställande av interpella-\r\ntioner</pre><pre>Talmannen hade i enlighet med tilläggsbestäm-\r\nmelse 1, 6 kap. 1 § riksdagsordningen fastställt att\r\nsenaste dag för framställande av interpellationer un-\r\nder innevarande riksmöte skulle vara fredagen den\r\n28 april.</pre><pre>6 §  Anmälan om fördröjda svar på interpella-\r\ntioner</pre><pre>Till riksdagen hade inkommit följande skrivelser:</pre><pre>Interpellation 1999/2000:231</pre><pre>Till riksdagen\r\nInterpellation 1999/2000:231 av Ragnwi Marce-\r\nlind (kd) om arbetsmarknaden och rehabilitering.\r\nInterpellationen kommer att besvaras tisdagen den\r\n21 mars 2000.\r\nSkälet till dröjsmålet är andra engagemang inbo-\r\nkade den 7 mars, den 10 mars, den 14 mars och\r\ntjänsteresa den 17 mars.\r\nStockholm den 14 februari 2000\r\nNäringsdepartementet\r\nBjörn Rosengren\r\nEnligt uppdrag\r\nDag Ekman\r\nExpeditionschef</pre><pre>Interpellation 1999/2000:227</pre><pre>Till riksdagen\r\nInterpellation 1999/2000:227 av Jan-Evert\r\nRådhström (m) om alkolås.\r\nInterpellationen kommer att besvaras tisdagen den\r\n21 mars 2000.\r\nSkälet till dröjsmålet är andra engagemang inbo-\r\nkade den 7 mars, den 10 mars, den 14 mars och\r\ntjänsteresa den 17 mars.\r\nStockholm den 14 februari 2000\r\nNäringsdepartementet\r\nBjörn Rosengren\r\nEnligt uppdrag\r\nDag Ekman\r\nExpeditionschef</pre><pre>Interpellation 1999/2000:215</pre><pre>Till riksdagen\r\nInterpellation 1999/2000:215 av Sten Andersson\r\n(m) om en konferens om kommunismens offer.\r\nInterpellationen kommer att besvaras av vice\r\nstatsministern tisdagen den 22 februari 2000.\r\nSkälet till dröjsmålet är utlandsresa och svårighe-\r\nter att hitta svarstillfälle.\r\nStockholm den 14 februari 2000\r\nEnligt uppdrag\r\nPer Virdesten\r\nRättschef</pre><pre>Interpellation 1999/2000:229</pre><pre>Till riksdagen\r\nInterpellation 1999/2000:229 av Karin Falkmer\r\n(m) om Simplex.\r\nInterpellationen kommer att besvaras fredagen\r\nden 10 mars 2000.\r\nSkälet till dröjsmålet är utlandsresa och tjänstere-\r\nsa den 7 mars.\r\nStockholm den 10 februari 2000\r\nNäringsdepartementet\r\nMona Sahlin\r\nEnligt uppdrag\r\nDag Ekman\r\nExpeditionschef</pre><pre>Interpellation 1999/2000:222</pre><pre>Till riksdagen\r\nInterpellation 1999/2000:222 av Karin Pilsäter\r\n(fp) om förutsättningar för långsiktig tillväxt.\r\nInterpellationen kommer att besvaras tisdagen den\r\n7 mars 2000.\r\nSkälet till dröjsmålet är stor arbetsanhopning och\r\nplenifri vecka.\r\nStockholm den 10 februari 2000\r\nFinansdepartementet\r\nBosse Ringholm</pre><pre>Interpellation 1999/2000:217</pre><pre>Till riksdagen\r\nInterpellation 1999/2000:217 av Gunnar Hökmark\r\n(m) om strukturella reformer för att höja Sveriges\r\nlångsiktiga tillväxtkapacitet.\r\nInterpellationen kommer att besvaras tisdagen den\r\n7 mars 2000.\r\nSkälet till dröjsmålet är stor arbetsanhopning och\r\nplenifri vecka.\r\nStockholm den 9 februari 2000\r\nFinansdepartementet\r\nBosse Ringholm</pre><pre>Interpellation 1999/2000:225</pre><pre>Till riksdagen\r\nInterpellation 1999/2000:225 av Göte Jonsson om\r\nfristående skolor.\r\nInterpellationen kommer att besvaras tisdagen den\r\n7 mars 2000.\r\nSkälet till dröjsmålet är stor arbetsbörda.\r\nStockholm den 11 februari 2000\r\nUtbildningsdepartementet\r\nIngegerd Wärnersson\r\nEnligt uppdrag\r\nStaffan Bengtsson\r\nStatssekreterare</pre><pre>Interpellation 1999/2000:226</pre><pre>Till riksdagen\r\nInterpellation 1999/2000:226 av Sten Andersson\r\nom ideologiskt motiverade brott.\r\nInterpellationen kommer att besvaras torsdagen\r\nden 9 mars 2000.\r\nSkälet till dröjsmålet är plenifri vecka i riksdagen\r\noch tjänsteresa.\r\nStockholm den 11 februari 2000\r\nJustitiedepartementet\r\nLaila Freivalds</pre><pre>Interpellation 1999/2000:221</pre><pre>Till riksdagen</pre><pre>Interpellation 1999/2000:221 av Karin Pilsäter om\r\nspädbarnsdöd och stöd till drabbade familjer.\r\nInterpellationen kommer att besvaras fredagen\r\nden 10 mars 2000.\r\nSkälet till dröjsmålet är att jag inte kunnat finna\r\nen debattdag som passar både interpellanten och mig.\r\nStockholm den 14 februari 2000\r\nSocialdepartementet\r\nLars Engqvist</pre><pre>7 §  Svar på interpellation 1999/2000:220 om\r\nriskfaktorer vid partnervåld</pre><pre>Anf.  1  Justitieminister LAILA\r\nFREIVALDS (s):\r\nHerr talman! Ulla-Britt Hagström har frågat mig\r\npå vilket sätt jag arbetar med att ta till vara interna-\r\ntionella erfarenheter vid arbetet med att motverka\r\nmisshandel av kvinnor, samt vilka åtgärder jag avser\r\nvidta för att förbättra riskbedömningen när det gäller\r\npartnervåld. Jag besvarar hennes fråga främst utifrån\r\nde områden jag som justitieminister ansvarar för.\r\nDet är oacceptabelt att kvinnor varje dag utsätts\r\nför en partners våld och att hemmet för många kvin-\r\nnor är den farligaste miljön att vistas i. Våldet mot\r\nkvinnor är något som angår oss alla. Detta är, som\r\nUlla-Britt Hagström säkert vet, utgångspunkten för\r\nmitt arbete i dessa frågor.\r\nMin och regeringens inställning i frågan har också\r\nkommit till klart uttryck genom kvinnofridsreformen,\r\nsom är ett samlat åtgärdsprogram mot mäns våld mot\r\nkvinnor. Den bygger på ett långvarigt utredningsar-\r\nbete för att fånga upp alla aspekter på hur sådant våld\r\nska kunna motverkas. Reformen omfattar, förutom\r\nlagstiftning, en mängd åtgärder för att förebygga\r\nmäns våld mot kvinnor och för att utsatta kvinnor ska\r\nfå ett bättre stöd och bemötande.\r\nTanken är att mäns våld mot kvinnor måste be-\r\nkämpas genom ett brett och långsiktigt arbete inom\r\nalla samhällets sektorer och på alla nivåer. Berörda\r\nmyndigheter har också fått gemensamma uppdrag av\r\nbetydelse i detta sammanhang. De ska regelbundet\r\nredovisa sina insatser till regeringen. Vissa myndig-\r\nheter har också fått särskilda uppdrag. Inom Rege-\r\nringskansliet har också en interdepartemental arbets-\r\ngrupp bildats för att följa upp kvinnofridsreformen.\r\nJustitiedepartementet deltar också aktivt i det in-\r\nternationella samarbetet, bl.a. inom EU, mot våld mot\r\nkvinnor och människohandel. Departementet har även\r\nunder flera år arbetat för att möjligheterna att före-\r\nbygga brott ska förbättras inom EU och för ett ökat\r\ninformationsutbyte mellan medlemsstaterna. Som en\r\nkonsekvens av bl.a. insatser från Sverige konstaterade\r\nstats- och regeringscheferna vid toppmötet i Tammer-\r\nfors i höstas att flera åtgärder bör vidtas för att för-\r\nbättra samarbetet i frågor som rör möjligheterna att\r\nförebygga brott. Också när det gäller frågor om skydd\r\nför och stöd till brottsoffer arbetar Sverige aktivt\r\ninom EU.\r\nBrottsförebyggande frågor kommer att vara prio-\r\nriterade under Sveriges ordförandeskap. En av de\r\nviktigaste åtgärderna inom detta område är att skapa\r\nen grund för en kontinuerlig uppbyggnad av aktuell\r\nkunskap om effektiva brottsförebyggande åtgärder\r\noch etablera någon form av fast nätverk som kan\r\ngarantera att kunskap tas till vara och sprids. En fråga\r\nsom särskilt kommer att uppmärksammas är just våld\r\ni nära relationer.\r\nInternationellt utbyte och internationella kontakter\r\när något som är utmärkande för forskning och ut-\r\nveckling. Att ta till vara internationella erfarenheter\r\nvid arbetet med att motverka bl.a. våld mot kvinnor är\r\ndärför en naturlig del i arbetet hos de myndigheter\r\ninom rättsväsendet som har en tydlig inriktning mot\r\nforsknings- och utvecklingsarbete. Det gäller t.ex.\r\nBrottsförebyggande rådet och Rättsmedicinalverket,\r\nmen också Brottsoffermyndigheten.\r\nJag vill här också tillägga att det synsätt som\r\nkvinnofridsreformen utgår från grundas på den kun-\r\nskap om våld mot kvinnor som kommit fram genom\r\ninternationell forskning.\r\nArbetet med att förbättra riskbedömningar pågår\r\npå flera olika sätt inom rättsväsendets myndigheter.\r\nPolisen i Västerbotten arbetar t.ex. för närvarande\r\nmed ett utvecklingsarbete kring skattningsinstrumen-\r\ntet SARA, som Ulla-Britt Hagström tar upp i sin\r\ninterpellation. Utvecklingsarbetet bedrivs i samarbete\r\nmed Rättspsykiatriska forskningsenheten i Växjö och\r\nsyftar till att utforma en SARA-modell som är anpas-\r\nsad till polisiära förutsättningar. Det diskuteras också\r\nför närvarande om liknande utvecklingsarbeten ska\r\npåbörjas av andra polismyndigheter.\r\nEtt arbete med att utveckla möjligheterna att göra\r\nsäkrare risk- och farlighetsbedömningar pågår också\r\ninom kriminalvården. I arbetet med dessa bedöm-\r\nningar av risk för återfall används vid ett flertal an-\r\nstalter olika hjälpmedel som t.ex. instrumentet HCR-\r\n20. Vid riksmottagningen på anstalten i Kumla har\r\nman även börjat att använda det tidigare nämnda\r\nSARA. På riksmottagningen utreds alla långtidsdöm-\r\nda män och en individuell riskprofil tas fram. Den\r\nanvänds som en del i bedömningen av vilka särskilda\r\nvillkor som ska gälla för långtidsdömda, bl.a. vid\r\npermissioner.\r\nInom ramen för ett pilotprojekt på Norrtäljean-\r\nstalten har också SARA samt ett särskilt instrument\r\nför att bedöma risken för återfall i sexuellt våld, kallat\r\nSVR-20, prövats. Inriktningen är att användningen av\r\nolika skattningsinstrument ska öka inom kriminalvår-\r\nden.\r\nRegeringen har vidare i regleringsbrevet för\r\nRättsmedicinalverket för år 2000 särskilt poängterat\r\natt verkets forsknings- och utvecklingsarbete ska\r\ninriktas mot att utveckla förutsättningarna för att göra\r\nsäkrare risk- och farlighetsbedömningar. Som ett led i\r\nutvecklingen på detta område kommer Rättsmedici-\r\nnalverket att under våren 2000 fastställa nya riktlinjer\r\nför riskbedömning vid rättspsykiatrisk undersökning.\r\nEn viktig faktor för att förbättra förutsättningarna\r\nför riskbedömningar är att myndigheter och andra\r\nsamarbetar kring frågan. Som ett led i ett sådant sam-\r\narbete har Brottsförebyggande rådet, Kriminalvårds-\r\nstyrelsen och Rättsmedicinalverket påbörjat en dis-\r\nkussion kring på vilka sätt myndigheterna gemensamt\r\nkan vidareutveckla arbetet på detta område.\r\nArbetet med riskbedömningar är ett viktigt och\r\nprioriterat område för nämnda myndigheter. Vi måste\r\ndock komma ihåg att hur förfinade olika skattningsin-\r\nstrument och andra hjälpmedel än blir kan de aldrig\r\nbli något annat än ett underlag för beslutsfattaren. När\r\nbeslut om en åtgärd väl ska fattas måste detta göras\r\nav en person som väger samman alla tillgängliga\r\nfakta och omständigheter i fallet.</pre><pre>Anf.  2  ULLA-BRITT HAGSTRÖM (kd):\r\nHerr talman! Jag vill tacka justitieministern för ett\r\nmycket seriöst och genomarbetat svar på min inter-\r\npellation om åtgärder mot partnervåldet. Det känns på\r\nnågot sätt som om vi arbetar gemensamt mot våldet\r\noch försöker gripa alla halmstrån. Uttrycket Mitt hem\r\när min borg står för det som för många kvinnor är den\r\nfarligaste miljön att vistas i. Hösten som föregick vårt\r\nnya millennium påminde oss gång på gång om kvin-\r\nnor som mördats av sina män. Detta i ett land som\r\nbetraktar sig som världens mest jämställda land, och\r\nkvinnor vi möter i internationella sammanhang, med\r\nden bild av Sverige de fått, tror inte att det är sant.\r\nVi har kommit långt med att implementera be-\r\ngreppet nollvision i trafiken. Men vi har inte lyckats\r\nfå det allmänt vedertaget att en nollvision vad gäller\r\nvåld mot kvinnor är en självklarhet, inte heller mot\r\nmobbning. Brist på empati, den etik som förvaltats av\r\nkristen tradition och västerländsk humanism, syns\r\ninte bara i den livliga skoldebatten. Vi försvagar\r\nständigt våra historiska rötter. Om inte t.ex. skolmi-\r\nnistern griper in nu kommer t.o.m. den religion vår\r\ntradition, våra lagar och vår kultur vilar på att för-\r\nsvinna från skolans kursplan. Ordet kristendom fanns\r\növer huvud taget inte nämnt i Skolverkets första ver-\r\nsion. Men i går sade skolministern i en debatt: Lita på\r\nmig! Så nu hoppas vi att hon griper in. Inom en må-\r\nnad kommer det svaret från regeringen.\r\nHerr talman! Det är inte acceptabelt att kvinnor\r\nska behöva leva med risken att utsättas för våld i\r\nhemmet. Varje år anmäls 20 000 fall av våldsbrott\r\nriktade mot kvinnor. Det är mer än 50 varje dag. Ett\r\nstort mörkertal finns också. Man säger generellt att\r\nendast 25 % av alla våldsbrott anmäls. Mörkertalet\r\nnär det gäller våld mot kvinnor är sannolikt större än\r\nför våldsbrott i allmänhet. Kvinnomisshandel har\r\nblivit en epidemi. Mot epidemier gör stora vaccina-\r\ntionskampanjer nytta. Men kvinnomisshandel har\r\nblivit en tyst epidemi.\r\nOm vi inte passar oss nu finns en risk för att re-\r\nspekten för människovärdet alltmer försämras i vårt\r\nland. Dokumentärfilmen Shocking truth är ytterligare\r\nen väckarklocka. Biografbyrån som utgår från en\r\nlagstiftning om förbud mot att visa sexuellt våld och\r\ntvång har inte ansett sig ha lagstöd för att stoppa\r\ndessa sektioner av porrfilm i t.ex. kanalen TV 1000.\r\nGranskningsnämnden anser sig inte ha något stöd i\r\nradio- och TV-lagen för att göra något. Detta utbud\r\nföder vi ungdomar med. Men vi föder också män som\r\nmisshandlar fruar, sambor, fästmör och andra närstå-\r\nende kvinnor. Norge har en starkare lagstiftning. Jag\r\nvädjar till justitieministern att se över om vår lagstift-\r\nning på det området är tillräcklig. Jag menar nu inte\r\nsjälva kvinnofridsreformen, utan det förebyggande\r\narbetet, där medieutbudet spelar en stor roll. Kvinno-\r\nfridsreformen tycker jag är mycket bra.\r\nMin interpellation handlar om olika metoder för\r\natt förbättra riskbedömningen inför partnervåld. Jag\r\när glad att justitieministern pekar på ett aktivt arbete\r\nför att finna nya metoder, både egna och internatio-\r\nnella erfarenheter tas till vara. Min fråga till ministern\r\när om SARA, den metod jag pekat på och som jag\r\nförstår används i Västerbotten liksom på Kumla- och\r\nNorrtäljeanstalterna, hittills har kunnat påvisa positi-\r\nva resultat, och hur använder man sig av den i Väs-\r\nterbotten på ett tidigare stadium för att kunna före-\r\nbygga?\r\nEfter vad jag förstår försvinner kvinnans livsut-\r\nrymme mer och mer i ett misshandelsförhållande, så\r\natt hon gradvis blir mer och mer beroende av den man\r\nsom misshandlar henne. De enda undersökningar av\r\nvad vidtagna åtgärder mot kvinnovåld har haft för\r\neffekter på våldets omfattning under 90-talet har jag\r\nsett är användningen av besöksförbudet.</pre><pre>Anf.  3  Justitieminister LAILA\r\nFREIVALDS (s):\r\nHerr talman! Ja, vi är stolta över att ha kommit\r\nlångt när det gäller jämställdhetsarbetet. Vi har också\r\nanledning att vara stolta över att frågan om våld i nära\r\nrelationer är någonting som vi inte accepterar.\r\nJag tycker däremot att det leder helt fel att tala om\r\natt vi har en epidemi. Då tror man att det är en sjuk-\r\ndom som sprider sig, ökar i omfattning och berör\r\nalltfler människor i samhället. Så är det inte. Det är\r\nfaktiskt tvärtom. Historiskt sett har vi ändå kommit\r\nen bit på väg när det gäller att inte acceptera våld i\r\nvårt samhälle, inte i något sammanhang. Från att inte\r\nför så länge sedan ha haft något som vi kallade för\r\nhusaga, då man ansåg att misshandel av närstående\r\ninte bara var bra utan var något som det t.o.m. var\r\nönskvärt att man utnyttjade i uppfostringssyfte, i\r\ndisciplinerande syfte, har vi kommit så långt att vi\r\nanser att varje övergrepp som görs mellan människor\r\när misshandel och ett brott som samhället har anled-\r\nning att reagera mot.\r\nDet finns heller ingenting som tyder på att det just\r\nnär det gäller våld i hemmet finns ett ökat våld. Den\r\nökning vi ser i anmälan av brott finns det stor anled-\r\nning att tro hänger samman med att detta är någonting\r\nsom har uppmärksammats och som gör att alltfler\r\nbarn och kvinnor vågar, orkar och förmår anmäla och\r\nsöka samhällets hjälp. Det ska vi vara väldigt glada\r\nför.\r\nNär det gäller att utveckla riskbedömningsmeto-\r\nder pågår det, som jag redogjorde för i mitt interpel-\r\nlationssvar, ett aktivt arbete, både inom polisens\r\nverksamhet och inom kriminalvården.\r\nTillämpningen av just metoden SARA är så ny\r\nännu att jag inte vågar uttala mig om vilka positiva\r\neffekter den har. Men jag utgår från, och har all an-\r\nledning att göra det med den allmänna erfarenhet vi\r\nhar, att tillämpningen av hjälpmetoder när det gäller\r\natt bedöma komplicerade situationer alltid leder till\r\natt de beslut som människor har att fatta, det må vara\r\npoliser eller kriminalvårdens personal, blir bättre ju\r\nmer systematisk behandling av olika faktorer man\r\ngör. Jag är övertygad om att SARA och de andra\r\nmetoderna kommer att leda till att bättre bedömningar\r\ngörs i förväg av när risk för våld föreligger, så att\r\nsamhället kan ingripa och förhindra det fortsatta vål-\r\ndet.</pre><pre>Anf.  4  ULLA-BRITT HAGSTRÖM (kd):\r\nHerr talman! Just ordet epidemi har jag tagit från\r\nKvinnomisshandel, den tysta epidemin, en nordisk\r\nkriminalkrönika, 1999, av Gun Heimer och Lars\r\nNylén.\r\nJag är glad att det kanske inte är så att misshan-\r\ndeln ökar, utan att man i stället vågar anmäla mer och\r\natt den statistik som visar ökning kan bero på det. I så\r\nfall är det enbart positivt.\r\nMen det är individer, kvinnor, som far illa. Det är\r\nfaktiskt så att medan vi skriver och debatterar om\r\nvåldet slås kvinnor sönder. Jag fick ett samtal från en\r\nkvinna som säger så här: Alla skrivningar om kvin-\r\nnovåld känns som ett hån, medan jag sitter inlåst här,\r\nmed kedjor runt balkongdörren.\r\nDet är alltfler kvinnor som hör av sig till oss. En\r\nkvinna, vars man fått besöksförbud fyra gånger och\r\nsom försökt slå ihjäl henne två gånger, upplever sig\r\nfortfarande inte ha något skydd. Efter tolv anmäl-\r\nningar och efter att ha spöats i fem år sitter kvinnan\r\ninlåst av skräcken, medan förövaren, mannen, går fri\r\nsom om ingenting hänt. Grannar vågar inget säga av\r\nrädsla för mannen. Polisen har tagit hans löfte att han\r\ninget ska göra på allvar, medan kvinnans skräck inte\r\nlett till någon åtgärd.\r\nHon säger så här: Ishockeyspelare blir tagna ur\r\nspel för hjärnskador, medan det är mindre viktigt med\r\nsönderslagna, misshandlade och missförstådda kvin-\r\nnor.\r\nSkälet till att polisen inte lyssnat på henne tror\r\nhon är att hon har blivit sönderslagen och fått en\r\nhuvudskada som inte läkt. Hon har därför tappat min-\r\nnet. Hon menar att det inte räcker att vid förhör fråga\r\nkvinnan om näven var knuten eller öppen. Det går\r\ninte att gradera misshandel för att få tillgång till\r\nlarmpaket. Varje misshandlad kvinnas röst måste tas\r\npå allvar.\r\nHerr talman! Rikskvinnocentrum pekar på det sto-\r\nra informationsbehovet för flera yrkeskategorier. Jag\r\när glad att justitieministern lyfter fram samarbetsfrå-\r\ngorna på alla nivåer. Den interdepartementala grup-\r\npen i regeringen är ett positivt initiativ. Jag hoppas att\r\ndär finns representanter för familj, skola, uppväxt-\r\nmiljö, bostad, arbetsmarknad, vård och finans.\r\nJag ser fram emot en livlig diskussion inför initia-\r\ntivet om brottsförebyggande frågor under Sveriges\r\nEU-ordförandeskap, just om temat våld i nära relatio-\r\nner.\r\nEn fråga som jag dock saknar i hela den här de-\r\nbatten är drogernas påverkan. Man säger att det yt-\r\nterst är mannens kontrollerande över kvinnan det\r\nhandlar om. Statsministern nämner inte heller drog-\r\nfrågorna i regeringsförklaringen. Detta tycker jag är\r\nsynd. Jag undrar om vi inte underskattar alkoholens\r\nbetydelse när det gäller misshandel av kvinnor, därför\r\natt mannens kontrollerande tvång kan förstärkas av\r\nalkohol.\r\nBesöksförbudet måste garantera att kvinnan inte\r\nblir uppsökt. Det måste finnas en skyddszon runt\r\nkvinnan så att hon inte blir inlåst i ett rum och kök.\r\nVi har inte tillräckligt många trygghetspaket och\r\nlarm. Det har också visat sig att inte ens elektronisk\r\nfotboja ger tillräcklig garanti. Hundar används för lite\r\ntill skydd för kvinnan. Det måste finnas mer att göra.\r\nJag skulle vilja fråga Laila Freivalds om polisens\r\nresurser och polisens attityder. Det blir inte bättre av\r\natt tingsrätter och domstolar läggs ned i besparings-\r\nsyfte och att poliskåren minskar. Hur kan vi skapa ett\r\nklimat där närpolisen blir informerad om misshandel\r\nså att kvinnor vågar anmäla?</pre><pre>Anf.  5  Justitieminister LAILA\r\nFREIVALDS (s):\r\nHerr talman! Varje polismyndighet har i uppdrag\r\natt utarbeta en handlingsplan för hur man ska agera\r\nnär det gäller att bekämpa våld i nära relationer. Det\r\ninnebär att polismyndigheten har det som en priorite-\r\nrad uppgift och att den hela tiden måste utveckla sina\r\nmetoder, sin kunskap och sin förmåga att hantera\r\ndetta.\r\nI polisens uppgifter ingår inte bara att reagera när\r\nbrott har begåtts, utan polisens uppgift är också att\r\nförebygga brott och att ge skydd och hjälp till dem\r\nsom blir utsatta för brott. Det är naturligtvis viktigt att\r\npolisen lyssnar när kvinnor berättar om sina upplevel-\r\nser. Det är viktigt att polisen har en tillräcklig kun-\r\nskap för att kunna tolka och rätt uppfatta den infor-\r\nmation de får och att då ta till det skydd och den hjälp\r\nkvinnan behöver.\r\nDet råder inget tvivel om att polisen behöver mer\r\nresurser för att kunna utveckla även den sidan av\r\nderas arbete. Såvitt jag vet har det aldrig hänt att\r\nnågon kvinna har blivit nekad hjälp på grund av att\r\nlarmpaket har saknats. Jag vet att det har förekommit\r\natt en polismyndighet har vänt sig till en annan i\r\nakuta situationer när det egna lagret av larmpaket har\r\nvarit slut. Men att man därigenom har varit tvungen\r\natt någon gång neka ett larmpaket när bedömningen\r\nhar gjorts att ett sådant behövs har jag inte hört talas\r\nom.\r\nAlkoholen har betydelse i våldssammanhang. Jag\r\ntror att forskningen med bestämdhet kan säga att\r\nalkoholen ibland är en utlösande faktor för våld som\r\nförekommer inte bara i hemmet utan också i samband\r\nmed nöjesliv och olika mänskliga sammanhang. Al-\r\nkoholen är därför ett problem i samhället även av det\r\nskälet. Vi har en restriktiv alkoholpolitik som syftar\r\ntill att förebygga alkoholens skador. Det är en fråga\r\nsom naturligtvis också måste uppmärksammas i sam-\r\nband med att vi utvecklar metoder och kunskap om\r\nvåld i hemmiljö.\r\nBesöksförbudet är en viktig åtgärd för att skapa\r\nnågot slags trygg situation för kvinnan. Det är ingen\r\nhundraprocentig metod. Dels vet vi att det överträds,\r\ndels vet vi att kvinnor inte alltid känner sig säkra på\r\natt det ger tillräckligt skydd. Brottsförebyggande\r\nrådet har haft i uppdrag att undersöka möjligheten att\r\nkombinera besöksförbud med elektronisk boja, och\r\ndet finns tekniska förutsättningar för att utveckla en\r\nsådan metod. Men vi ska inte ha någon överdriven\r\nuppfattning om att detta skyddar kvinnan. Den man\r\nsom har bestämt sig för att bryta mot ett besöksförbud\r\nutlöser också larmanordningen i den elektroniska\r\nbojan. Men det kan vara en metod att avslöja flera fall\r\nav brott mot besöksförbudet. Men för att skydda\r\nkvinnan måste våra ambitioner vara högre, och vi\r\nmåste utveckla andra metoder.</pre><pre>Anf.  6  ULLA-BRITT HAGSTRÖM (kd):\r\nHerr talman! Jag tackar för svaret. Det är viktigt\r\natt handlingsplanen följs och att det finns dokumen-\r\ntation. Sekretessen måste hållas, t.ex. får inte en\r\nhemlig adress lämnas ut. En kvinna ska inte behöva\r\nsitta förtvivlad på en vårdcentral och inte känna sig\r\ntrygg för att hon inte kan ha en adress i vårdcentra-\r\nlens databas. Det finns sådant som för oss är småsa-\r\nker som har stor betydelse för dessa kvinnor som vi\r\nmåste se över gemensamt.\r\nJag är också glad att justitieministern talar om al-\r\nkoholens påverkan. Vi verkar vara överens om alko-\r\nholen som en utlösande faktor. Det är synd att vi inte\r\ni riksdagen kan ta ett gemensamt initiativ så att vi\r\nt.ex. kan behålla de införselregler vi har och inte\r\nanamma EU:s införselregler vad gäller alkohol. Det\r\när synd att det har upprättats Internetkanaler och\r\ndirektkontakter med kommissionären Frits Bolkestein\r\noch att vi inte kan uppträda som ett gemensamt par-\r\nlament i frågan. Jag tycker att vissa uppträder osoli-\r\ndariskt i frågan.\r\nVi måste alltmer lyfta fram i fokus av våldet gär-\r\nningsmannen. Hittills har det mest varit offrets bete-\r\nende som har varit intressant. Vi behöver mer av\r\nsjälvskattningsinstrument. Det finns människor som\r\nvill hjälpa till men som inte tas till vara. Det kan vara\r\nt.ex. far- och morföräldrar som bygger nätverk och\r\nsom försöker hjälpa sina döttrar mot våldet.\r\nSlutligen vill jag säga någonting om attityder. Det\r\ngäller t.ex. den allvarliga frågan om trafficking. Tjejer\r\nfrån Baltikum luras hit i dessa syften. I A Story About\r\nTraffic Signs används kvinnor i vägmärkesdiskussio-\r\nnen: \"- - - when I saw a woman lying down.\" Detta\r\när så felaktiga attityder som påverkar frågorna.</pre><pre>Överläggningen var härmed avslutad.</pre><pre>8 §  Hänvisning av ärenden till utskott</pre><pre>Föredrogs och hänvisades\r\nProposition\r\n1999/2000:59 till justitieutskottet</pre><pre>Redogörelse\r\n1999/2000:RB1 till finansutskottet</pre><pre>Motion\r\n1999/2000:Sk20 till skatteutskottet</pre><pre>9 §  Bordläggning</pre><pre>Anmäldes och bordlades\r\nFörslag\r\n1999/2000:RR8 Riksdagens revisorers förslag angå-\r\nende statliga kreditgarantier</pre><pre>Konstitutionsutskottets betänkande\r\n1999/2000:KU14 Upphovsrätten och offentlighets-\r\nprincipen</pre><pre>Lagutskottets betänkande\r\n1999/2000:LU9 Aktiebolags förvärv och överlåtelser\r\nav egna aktier</pre><pre>Skatteutskottets betänkande\r\n1999/2000:SkU12 Vissa skattefrågor med anledning\r\nav att aktiebolag skall kunna förvärva egna aktier,\r\nm.m.</pre><pre>Finansutskottets betänkande\r\n1999/2000:FiU15 Vissa finansmarknads-, försäk-\r\nringsrörelse- och kreditupplysningsfrågor</pre><pre>Bostadsutskottets betänkanden\r\n1999/2000:BoU4 Statligt stöd till lokala investerings-\r\nprogram\r\n1999/2000:BoU5 Vissa indelnings- och länsstyrelse-\r\nfrågor</pre><pre>Justitieutskottets betänkande\r\n1999/2000:JuU8 Hemlig teleavlyssning, m.m.</pre><pre>10 §  Anmälan om frågor för skriftliga svar</pre><pre>Anmäldes att följande frågor för skriftliga svar\r\nframställts</pre><pre>den 17 februari</pre><pre>1999/2000:575 av Yvonne Ångström (fp) till statsrå-\r\ndet Maj-Inger Klingvall\r\nFamiljen Sincari\r\n1999/2000:576 av Sinikka Bohlin (s) till jordbruks-\r\nminister Margareta Winberg\r\nForskning kring lax och öring\r\n1999/2000:577 av Mikael Odenberg (m) till närings-\r\nminister Björn Rosengren\r\nVägverkets handläggning av taxiförarlegitimation\r\n1999/2000:578 av Eva Arvidsson (s) till statsrådet\r\nUlrica Messing\r\nIntegrationsverket</pre><pre>den 18 februari</pre><pre>1999/2000:579 av Eva Arvidsson (s) till statsrådet\r\nIngegerd Wärnersson\r\nFristående skolor\r\n1999/2000:580 av Chatrine Pålsson (kd) till statsrå-\r\ndet Maj-Inger Klingvall\r\nInvandrares ersättning under grundskoleutbildning</pre><pre>Frågorna redovisas i bilaga som fogas till riksda-\r\ngens snabbprotokoll tisdagen den 22 februari.</pre><pre>11 §  Kammaren åtskildes kl. 9.26.</pre><pre>\r\nFörhandlingarna leddes av förste vice talmannen.</pre>\r\n"},"dokaktivitet":null,"dokintressent":null,"dokforslag":null,"dokuppgift":null,"dokbilaga":null,"dokreferens":null,"debatt":null}}