{"dokumentstatus":{"dokument":{"hangar_id":"2348795","dok_id":"GL097","rm":"1997/98","beteckning":"7","doktyp":"prot","typ":"prot","subtyp":null,"tempbeteckning":null,"organ":null,"mottagare":null,"nummer":"7","slutnummer":"0","datum":"1997-09-26 00:00:00","systemdatum":"2005-10-27 13:10:07","publicerad":"1997-09-26 00:00:00","titel":"Riksdagens snabbprotokoll 1997/98:7 Fredagen den 26 september","subtitel":null,"status":null,"htmlformat":null,"relaterat_id":null,"source":"webbnav","sourceid":"{5F0C300C-DBFD-4E0B-B42A-8BBE4EAF0F43}","dokument_url_text":"http://data.riksdagen.se/dokument/GL097/text","dokument_url_html":"http://data.riksdagen.se/dokument/GL097","dokumentstatus_url_xml":"http://data.riksdagen.se/dokumentstatus/GL097","html":"\r\n<br><div class=\"sidhuvud_publikation\">Riksdagens snabbprotokoll</div>\r\n<div class=\"sidhuvud_beteckning\">Protokoll 1997/98:7</div>\r\n<div class=\"sidhuvud_datum\">Fredagen den 26 september</div>\r\n<div class=\"sidhuvud_klockslag\">Kl. 13.00 - 13.01</div>\r\n<hr class=\"sidhuvud_linje\">\r\n<pre>Det justerade protokollet beräknas utkomma om 3 veckor</pre><pre>\r\n------------------------------------------------------------------</pre><pre>1 §  Avsägelse</pre><pre>Förste vice talmannen meddelade att Monica Öh-\r\nman (s) avsagt sig uppdraget som ledamot i EU-\r\nnämnden fr.o.m. den 1 oktober.</pre><pre>Kammaren biföll denna ansökan.</pre><pre>2 §  Meddelande om frågestund</pre><pre>Förste vice talmannen meddelade att vid fråge-\r\nstunden torsdagen den 2 oktober kl. 14.00 skulle\r\nföljande statsråd närvara:\r\nStatsminister Göran Persson, statsrådet Pierre\r\nSchori, näringsminister Anders Sundström, miljömi-\r\nnister Anna Lindh, statsrådet Ylva Johansson, för-\r\nsvarsminister Björn von Sydow och statsrådet Tho-\r\nmas Östros.</pre><pre>3 §  Anmälan om inkommen faktapromemoria\r\nom förslag från Europeiska kommissionen</pre><pre>Förste vice talmannen meddelade att följande\r\nfaktapromemoria om förslag från Europeiska kom-\r\nmissionen inkommit och delats ut till kammarens\r\nledamöter:\r\nFörslag till rådets direktiv om anpassning till den\r\ntekniska och vetenskapliga utvecklingen av direk-\r\ntiv om bevarande av livsmiljöer samt vilda djur\r\noch växter KOM (97) 195</pre><pre>4 §  Hänvisning av ärende till utskott</pre><pre>Föredrogs och hänvisades\r\nProposition\r\n1997/98:3 till socialförsäkringsutskottet</pre><pre>5 §  Bordläggning</pre><pre>Anmäldes och bordlades\r\nProposition\r\n1997/97:18 Utvidgade möjligheter till inköp mot\r\nförsäkran enligt lagen om skatt på energi, m.m.</pre><pre>6 §  Anmälan om frågor för skriftliga svar</pre><pre>Anmäldes att följande frågor för skriftliga svar\r\nframställts</pre><pre>den 26 september</pre><pre>1997/98:26 av Margitta Edgren (fp) till utbild-\r\nningsministern\r\nAntagningen till universitet och högskola\r\n1997/98:27 av Per Sundgren (v) till finansministern\r\nChefslönerna i stat och kommun\r\n1997/98:28 av Kenth Skårvik (fp) till kommunika-\r\ntionsministern\r\nS.k. trefältsvägar</pre><pre>Frågorna redovisas i bilaga som fogas till riksda-\r\ngens snabbprotokoll onsdagen den 1 oktober.</pre><pre>7 §  Kammaren åtskildes kl. 13.01.</pre><pre>\r\nFörhandlingarna leddes av förste vice talmannen.</pre>\r\n"},"dokaktivitet":null,"dokintressent":null,"dokforslag":null,"dokuppgift":null,"dokbilaga":null,"dokreferens":null,"debatt":null}}